[
  {"code": "ARG", "name": "Argentina",      "name_pt": "Argentina",       "confederation": "CONMEBOL", "fifa_ranking": 1,  "group": "E", "api_football_id": 26,   "football_data_id": 64},
  {"code": "FRA", "name": "France",         "name_pt": "França",          "confederation": "UEFA",     "fifa_ranking": 2,  "group": "G", "api_football_id": 2,    "football_data_id": 66},
  {"code": "ENG", "name": "England",        "name_pt": "Inglaterra",      "confederation": "UEFA",     "fifa_ranking": 3,  "group": "I", "api_football_id": 10,   "football_data_id": 66},
  {"code": "BEL", "name": "Belgium",        "name_pt": "Bélgica",         "confederation": "UEFA",     "fifa_ranking": 4,  "group": "C", "api_football_id": 1,    "football_data_id": 68},
  {"code": "BRA", "name": "Brazil",         "name_pt": "Brasil",          "confederation": "CONMEBOL", "fifa_ranking": 5,  "group": "F", "api_football_id": 6,    "football_data_id": 63},
  {"code": "POR", "name": "Portugal",       "name_pt": "Portugal",        "confederation": "UEFA",     "fifa_ranking": 6,  "group": "K", "api_football_id": 27,   "football_data_id": 765},
  {"code": "NED", "name": "Netherlands",    "name_pt": "Holanda",         "confederation": "UEFA",     "fifa_ranking": 7,  "group": "I", "api_football_id": 1044, "football_data_id": 784},
  {"code": "COL", "name": "Colombia",       "name_pt": "Colômbia",        "confederation": "CONMEBOL", "fifa_ranking": 8,  "group": "D", "api_football_id": 31,   "football_data_id": null},
  {"code": "ESP", "name": "Spain",          "name_pt": "Espanha",         "confederation": "UEFA",     "fifa_ranking": 9,  "group": "H", "api_football_id": 9,    "football_data_id": 760},
  {"code": "ITA", "name": "Italy",          "name_pt": "Itália",          "confederation": "UEFA",     "fifa_ranking": 9,  "group": "K", "api_football_id": 768,  "football_data_id": 784},
  {"code": "URU", "name": "Uruguay",        "name_pt": "Uruguai",         "confederation": "CONMEBOL", "fifa_ranking": 10, "group": "E", "api_football_id": 34,   "football_data_id": null},
  {"code": "USA", "name": "United States",  "name_pt": "Estados Unidos",  "confederation": "CONCACAF", "fifa_ranking": 11, "group": "A", "api_football_id": 1,    "football_data_id": 762},
  {"code": "GER", "name": "Germany",        "name_pt": "Alemanha",        "confederation": "UEFA",     "fifa_ranking": 12, "group": "J", "api_football_id": 25,   "football_data_id": 759},
  {"code": "MEX", "name": "Mexico",         "name_pt": "México",          "confederation": "CONCACAF", "fifa_ranking": 13, "group": "B", "api_football_id": 16,   "football_data_id": null},
  {"code": "CRO", "name": "Croatia",        "name_pt": "Croácia",         "confederation": "UEFA",     "fifa_ranking": 14, "group": "J", "api_football_id": 3,    "football_data_id": null},
  {"code": "MAR", "name": "Morocco",        "name_pt": "Marrocos",        "confederation": "CAF",      "fifa_ranking": 14, "group": "C", "api_football_id": 1,    "football_data_id": null},
  {"code": "JPN", "name": "Japan",          "name_pt": "Japão",           "confederation": "AFC",      "fifa_ranking": 15, "group": "F", "api_football_id": 21,   "football_data_id": null},
  {"code": "SEN", "name": "Senegal",        "name_pt": "Senegal",         "confederation": "CAF",      "fifa_ranking": 20, "group": "G", "api_football_id": 37,   "football_data_id": null},
  {"code": "IRN", "name": "Iran",           "name_pt": "Irã",             "confederation": "AFC",      "fifa_ranking": 22, "group": "M", "api_football_id": 1044, "football_data_id": null},
  {"code": "KOR", "name": "South Korea",    "name_pt": "Coreia do Sul",   "confederation": "AFC",      "fifa_ranking": 23, "group": "K", "api_football_id": 4,    "football_data_id": null},
  {"code": "AUS", "name": "Australia",      "name_pt": "Austrália",       "confederation": "AFC",      "fifa_ranking": 23, "group": "L", "api_football_id": 35,   "football_data_id": null},
  {"code": "DEN", "name": "Denmark",        "name_pt": "Dinamarca",       "confederation": "UEFA",     "fifa_ranking": 21, "group": "L", "api_football_id": 21,   "football_data_id": null},
  {"code": "SUI", "name": "Switzerland",    "name_pt": "Suíça",           "confederation": "UEFA",     "fifa_ranking": 19, "group": "L", "api_football_id": 7,    "football_data_id": null},
  {"code": "POL", "name": "Poland",         "name_pt": "Polônia",         "confederation": "UEFA",     "fifa_ranking": 26, "group": "H", "api_football_id": 24,   "football_data_id": null},
  {"code": "SRB", "name": "Serbia",         "name_pt": "Sérvia",          "confederation": "UEFA",     "fifa_ranking": 33, "group": "H", "api_football_id": 1044, "football_data_id": null},
  {"code": "AUT", "name": "Austria",        "name_pt": "Áustria",         "confederation": "UEFA",     "fifa_ranking": 25, "group": "N", "api_football_id": 1044, "football_data_id": null},
  {"code": "UKR", "name": "Ukraine",        "name_pt": "Ucrânia",         "confederation": "UEFA",     "fifa_ranking": 22, "group": "N", "api_football_id": 1044, "football_data_id": null},
  {"code": "TUR", "name": "Turkey",         "name_pt": "Turquia",         "confederation": "UEFA",     "fifa_ranking": 36, "group": "O", "api_football_id": 1044, "football_data_id": null},
  {"code": "CAN", "name": "Canada",         "name_pt": "Canadá",          "confederation": "CONCACAF", "fifa_ranking": 49, "group": "C", "api_football_id": 95,   "football_data_id": null},
  {"code": "ECU", "name": "Ecuador",        "name_pt": "Equador",         "confederation": "CONMEBOL", "fifa_ranking": 30, "group": "D", "api_football_id": 1044, "football_data_id": null},
  {"code": "GHA", "name": "Ghana",          "name_pt": "Gana",            "confederation": "CAF",      "fifa_ranking": 60, "group": "N", "api_football_id": 22,   "football_data_id": null},
  {"code": "CMR", "name": "Cameroon",       "name_pt": "Camarões",        "confederation": "CAF",      "fifa_ranking": 43, "group": "O", "api_football_id": 36,   "football_data_id": null},
  {"code": "TUN", "name": "Tunisia",        "name_pt": "Tunísia",         "confederation": "CAF",      "fifa_ranking": 28, "group": "I", "api_football_id": 28,   "football_data_id": null},
  {"code": "EGY", "name": "Egypt",          "name_pt": "Egito",           "confederation": "CAF",      "fifa_ranking": 35, "group": "O", "api_football_id": 1044, "football_data_id": null},
  {"code": "NGA", "name": "Nigeria",        "name_pt": "Nigéria",         "confederation": "CAF",      "fifa_ranking": 37, "group": "F", "api_football_id": 38,   "football_data_id": null},
  {"code": "SAU", "name": "Saudi Arabia",   "name_pt": "Arábia Saudita",  "confederation": "AFC",      "fifa_ranking": 56, "group": "J", "api_football_id": 1044, "football_data_id": null},
  {"code": "QAT", "name": "Qatar",          "name_pt": "Catar",           "confederation": "AFC",      "fifa_ranking": 37, "group": "M", "api_football_id": 1044, "football_data_id": null},
  {"code": "CRC", "name": "Costa Rica",     "name_pt": "Costa Rica",      "confederation": "CONCACAF", "fifa_ranking": 51, "group": "D", "api_football_id": 1044, "football_data_id": null},
  {"code": "PAN", "name": "Panama",         "name_pt": "Panamá",          "confederation": "CONCACAF", "fifa_ranking": 49, "group": "A", "api_football_id": 1044, "football_data_id": null},
  {"code": "JAM", "name": "Jamaica",        "name_pt": "Jamaica",         "confederation": "CONCACAF", "fifa_ranking": 50, "group": "B", "api_football_id": 1044, "football_data_id": null},
  {"code": "HON", "name": "Honduras",       "name_pt": "Honduras",        "confederation": "CONCACAF", "fifa_ranking": 78, "group": "B", "api_football_id": 1044, "football_data_id": null},
  {"code": "CHI", "name": "Chile",          "name_pt": "Chile",           "confederation": "CONMEBOL", "fifa_ranking": 32, "group": "E", "api_football_id": 7,    "football_data_id": null},
  {"code": "PER", "name": "Peru",           "name_pt": "Peru",            "confederation": "CONMEBOL", "fifa_ranking": 40, "group": "P", "api_football_id": 1044, "football_data_id": null},
  {"code": "PAR", "name": "Paraguay",       "name_pt": "Paraguai",        "confederation": "CONMEBOL", "fifa_ranking": 65, "group": "P", "api_football_id": 1044, "football_data_id": null},
  {"code": "VEN", "name": "Venezuela",      "name_pt": "Venezuela",       "confederation": "CONMEBOL", "fifa_ranking": 57, "group": "G", "api_football_id": 1044, "football_data_id": null},
  {"code": "BOL", "name": "Bolivia",        "name_pt": "Bolívia",         "confederation": "CONMEBOL", "fifa_ranking": 85, "group": "A", "api_football_id": 1044, "football_data_id": null},
  {"code": "NZL", "name": "New Zealand",    "name_pt": "Nova Zelândia",   "confederation": "OFC",      "fifa_ranking": 95, "group": "M", "api_football_id": 1044, "football_data_id": null}
]
